deeppype/__init__.py
deeppype/components/Configurator.py
deeppype/components/Connectors.py
deeppype/components/Pipe.py
deeppype/components/__init__.py
deeppype/components/inference/__init__.py
deeppype/components/inference/code/__init__.py
deeppype/components/inference/code/inference.py
deeppype/data/ImageDataset.py
deeppype/data/__init__.py
deeppype/models/__init__.py
deeppype/models/architectures.py
deeppype/models/model.py
deeppype-0.4.1.dist-info/LICENSE
deeppype-0.4.1.dist-info/METADATA
deeppype-0.4.1.dist-info/WHEEL
deeppype-0.4.1.dist-info/top_level.txt
deeppype-0.4.1.dist-info/RECORD
