Metadata-Version: 2.1
Name: deeppype
Version: 0.4.1
Summary: The AWS based Deep Learning Pipeline Framework
Home-page: UNKNOWN
Author: Marco Placenti
Author-email: s202798@student.dtu.dk
License: MIT
Project-URL: Source Code, https://github.com/marcoplacenti/deeppype
Platform: UNKNOWN
Requires-Python: >=3.9
License-File: LICENSE
Requires-Dist: torch
Requires-Dist: torchvision
Requires-Dist: numpy
Requires-Dist: pandas
Requires-Dist: opencv-python
Requires-Dist: pillow
Requires-Dist: argparse
Requires-Dist: pyyaml
Requires-Dist: scikit-learn
Requires-Dist: wandb
Requires-Dist: uuid
Requires-Dist: pytorch-lightning
Requires-Dist: pytorch-lightning-bolts
Requires-Dist: ray[tune]
Requires-Dist: boto3
Requires-Dist: botocore
Requires-Dist: sagemaker
Requires-Dist: python-dotenv
